heresycardbuilder/__init__.py
heresycardbuilder/asset_gui.py
heresycardbuilder/build_deck.py
heresycardbuilder/build_pdf.py
heresycardbuilder/build_tts.py
heresycardbuilder/card_editor.py
heresycardbuilder/card_editor_main.py
heresycardbuilder/card_editor_main.ui
heresycardbuilder/card_editor_res.qrc
heresycardbuilder/card_editor_res_rc.py
heresycardbuilder/card_objects.py
heresycardbuilder/card_render.py
heresycardbuilder/graphics_item_handles.py
heresycardbuilder/resizer.py
heresycardbuilder/spelltextedit.py
heresycardbuilder/ui_card_editor_main.py
heresycardbuilder/utilities.py
heresycardbuilder/view_widgets.py
heresycardbuilder-0.9.1.dist-info/LICENSE
heresycardbuilder-0.9.1.dist-info/METADATA
heresycardbuilder-0.9.1.dist-info/WHEEL
heresycardbuilder-0.9.1.dist-info/entry_points.txt
heresycardbuilder-0.9.1.dist-info/top_level.txt
heresycardbuilder-0.9.1.dist-info/RECORD
