Metadata-Version: 2.2
Name: heresycardbuilder
Version: 0.9.1
Summary: Tools for creating T.I.M.E Stories decks and building card images
Author-email: Randall Frank <frogboots.000@gmail.com>
Maintainer-email: Randall Frank <frogboots.000@gmail.com>
License: MIT License
Project-URL: Homepage, http://heresy.mrtrashcan.com/
Project-URL: Repository, https://github.com/randall-frank/heresy-card-builder.git
Project-URL: Issues, https://github.com/randall-frank/heresy-card-builder/issues
Project-URL: Changelog, https://github.com/randall-frank/heresy-card-builder/blob/master/CHANGELOG.md
Classifier: Development Status :: 4 - Beta
Classifier: License :: OSI Approved :: MIT License
Classifier: Operating System :: OS Independent
Classifier: Programming Language :: Python :: 3.10
Classifier: Programming Language :: Python :: 3.11
Classifier: Programming Language :: Python :: 3.12
Requires-Python: >=3.10
License-File: LICENSE
Requires-Dist: PySide6>=6.2.2
Requires-Dist: pyspellchecker>=0.6.3
Provides-Extra: dev
Requires-Dist: PySide6>=6.2.2; extra == "dev"
Requires-Dist: pyspellchecker>=0.6.3; extra == "dev"
Requires-Dist: build>=0.10.0; extra == "dev"
Requires-Dist: pre-commit>=3.3.3; extra == "dev"
Requires-Dist: setuptools>68.0.0; extra == "dev"
Requires-Dist: twine>6.0.0; extra == "dev"
Provides-Extra: doc
Requires-Dist: Sphinx==8.0.2; extra == "doc"
Requires-Dist: numpydoc==1.8.0; extra == "doc"
Requires-Dist: sphinx-copybutton==0.5.2; extra == "doc"
Requires-Dist: requests>=2.28.2; extra == "doc"
Provides-Extra: tests
Requires-Dist: pytest==8.3.2; extra == "tests"
